TinyLean/__init__.py
TinyLean/__main__.py
TinyLean/ast.py
TinyLean/grammar.py
TinyLean/ir.py
TinyLean/tests/__init__.py
TinyLean/tests/test_checker.py
TinyLean/tests/test_main.py
TinyLean/tests/test_parser.py
TinyLean/tests/test_resolver.py
tinylean-0.7.0.dist-info/LICENSE
tinylean-0.7.0.dist-info/METADATA
tinylean-0.7.0.dist-info/WHEEL
tinylean-0.7.0.dist-info/entry_points.txt
tinylean-0.7.0.dist-info/top_level.txt
tinylean-0.7.0.dist-info/RECORD
