Metadata-Version: 2.2
Name: TinyLean
Version: 0.7.0
Summary: Tiny theorem prover with syntax like Lean 4
Author-email: Anqur <anqurvanillapy@gmail.com>
License: MIT License
Project-URL: Homepage, https://github.com/anqurvanillapy/TinyLean
Project-URL: Bug Reports, https://github.com/anqurvanillapy/TinyLean/issues
Project-URL: Source, https://github.com/anqurvanillapy/TinyLean
Keywords: lean,lean4,theorem-proving,theorem-prover,programming-language
Classifier: Intended Audience :: Education
Classifier: Topic :: Education
Classifier: License :: OSI Approved :: MIT License
Classifier: Programming Language :: Python :: 3
Classifier: Programming Language :: Python :: 3.12
Classifier: Programming Language :: Python :: 3.13
Classifier: Programming Language :: Python :: 3 :: Only
Requires-Python: >=3.12
License-File: LICENSE
Requires-Dist: pyparsing==3.2.1
